{
    "author":  "GaoShou",
    "description":  "我重临王座之日，诸逆臣应当死去。",
    "supportedJobs":  [
                          {
                              "job":  "DRK",
                              "contentScope":  "HighEnd"
                          },
                          {
                              "job":  "RDM",
                              "contentScope":  "HighEnd"
                          }
                      ],
    "apiVersion":  15,
    "referencePromeVersion":  "1.5.3.2",
    "sponsorUrl":  "https://ifdian.net/a/GaoShou",
    "version":  "1.0.14.0",
    "sha256":  "c45f14b107f0a64e8c7e00d56b0d4491155ca939757d225a579bb8be6c93523e",
    "downloadUrl":  "https://github.com/Gaoshou0v0/PR-acr/raw/main/GaoShou.zip"
}